pyFixedWidthDataFile/__init__.py
pyFixedWidthDataFile/errors.py
pyFixedWidthDataFile/registro.py
pyFixedWidthDataFile/version.py
pyFixedWidthDataFile-0.0.6.dist-info/LICENSE.txt
pyFixedWidthDataFile-0.0.6.dist-info/METADATA
pyFixedWidthDataFile-0.0.6.dist-info/WHEEL
pyFixedWidthDataFile-0.0.6.dist-info/top_level.txt
pyFixedWidthDataFile-0.0.6.dist-info/RECORD
